stock_prediction/__init__.py
stock_prediction/core/__init__.py
stock_prediction/core/autotrade.py
stock_prediction/core/hmm_model.py
stock_prediction/core/models.py
stock_prediction/core/predictor.py
stock_prediction/utils/__init__.py
stock_prediction/utils/analysis.py
stock_prediction/utils/filter_script.py
stock_prediction/utils/preprocessing.py
stock_prediction_sta410-0.1.6.dist-info/LICENSE
stock_prediction_sta410-0.1.6.dist-info/METADATA
stock_prediction_sta410-0.1.6.dist-info/WHEEL
stock_prediction_sta410-0.1.6.dist-info/top_level.txt
stock_prediction_sta410-0.1.6.dist-info/RECORD
