Metadata-Version: 2.2
Name: stock_prediction_STA410
Version: 0.1.6
License-File: LICENSE
Requires-Dist: numpy==1.26.4
Requires-Dist: pandas
Requires-Dist: yfinance
Requires-Dist: scikit-learn==1.6.1
Requires-Dist: statsmodels
Requires-Dist: xgboost
Requires-Dist: lightgbm
Requires-Dist: catboost
Requires-Dist: matplotlib
Requires-Dist: seaborn
Requires-Dist: pandas-market-calendars
Requires-Dist: pandas_market_calendars
Requires-Dist: mplcursors
Requires-Dist: scikit-optimize
Requires-Dist: hmmlearn
Requires-Dist: pmdarima
Requires-Dist: statsforecast
Requires-Dist: pygam
Requires-Dist: schedule
Requires-Dist: alpaca_trade_api
Requires-Dist: alpaca
Requires-Dist: pyticksymbols
Dynamic: requires-dist
